gpeopleapiwrapper/__init__.py
gpeopleapiwrapper/auth.py
gpeopleapiwrapper/base.py
gpeopleapiwrapper/client.py
gpeopleapiwrapper/groups.py
gpeopleapiwrapper/persons.py
gpeopleapiwrapper-0.3.dist-info/LICENSE
gpeopleapiwrapper-0.3.dist-info/METADATA
gpeopleapiwrapper-0.3.dist-info/WHEEL
gpeopleapiwrapper-0.3.dist-info/top_level.txt
gpeopleapiwrapper-0.3.dist-info/RECORD
