Metadata-Version: 2.1
Name: gpeopleapiwrapper
Version: 0.3
Summary: A wrapper around the Google People API
Author-email: Martin Holtschneider <code@martin-holtschneider.de>
License: MIT
Project-URL: Homepage, https://github.com/holtschn/gpeopleapiwrapper
Classifier: Development Status :: 3 - Alpha
Classifier: Programming Language :: Python :: 3
Classifier: Operating System :: OS Independent
Classifier: Intended Audience :: Developers
Classifier: Topic :: Software Development :: Build Tools
Classifier: License :: OSI Approved :: MIT License
Classifier: Programming Language :: Python :: 3.9
Classifier: Programming Language :: Python :: 3.10
Classifier: Programming Language :: Python :: 3.11
Requires-Python: >=3.9
License-File: LICENSE
Requires-Dist: google-api-python-client >=2.84.0
Requires-Dist: google-auth-oauthlib >=0.1.0
Requires-Dist: ratelimit >=2.2.1
Provides-Extra: publish
Requires-Dist: build >=0.10.0 ; extra == 'publish'
Requires-Dist: twine >=4.0.2 ; extra == 'publish'
Provides-Extra: test
Requires-Dist: coverage >=7.2.3 ; extra == 'test'
Requires-Dist: pylama >=8.4.0 ; extra == 'test'
